compute_eval/__init__.py
compute_eval/data.py
compute_eval/evaluation.py
compute_eval/execution.py
compute_eval/generate_completions.py
compute_eval/main.py
compute_eval/prompts.py
compute_eval/models/claude.py
compute_eval/models/model_interface.py
compute_eval/models/nim_model.py
compute_eval/models/openAI_model.py
core_evals/compute_eval/__init__.py
core_evals/compute_eval/framework.yml
core_evals/compute_eval/framework_entrypoint.py
core_evals/compute_eval/output.py
data/LICENSE
data/cccl_problems_033125.jsonl
data/combined_problems_033125.jsonl
data/cuda_problems_033125.jsonl
data/example_test.jsonl
data/example_test_generation.jsonl
nvidia_compute_eval-25.11.dist-info/licenses/LICENSE
nvidia_compute_eval-25.11.dist-info/METADATA
nvidia_compute_eval-25.11.dist-info/WHEEL
nvidia_compute_eval-25.11.dist-info/entry_points.txt
nvidia_compute_eval-25.11.dist-info/top_level.txt
nvidia_compute_eval-25.11.dist-info/RECORD
