Metadata-Version: 2.4
Name: nvidia-compute-eval
Version: 25.11
Summary: Library for evaluating Large Language Models on CUDA code
Author: NVIDIA
Requires-Python: >=3.10
License-File: LICENSE
Requires-Dist: anthropic>=0.42.0
Requires-Dist: fire>=0.7.0
Requires-Dist: numpy>=2.2.0
Requires-Dist: openai>=1.58.1
Requires-Dist: pre-commit>=4.0.1
Requires-Dist: psutil>=6.1.1
Requires-Dist: python-dotenv>=1.0.1
Requires-Dist: requests>=2.32.3
Requires-Dist: tabulate>=0.9.0
Requires-Dist: tqdm>=4.67.1
Requires-Dist: nemo-evaluator
Dynamic: license-file
